mock/__init__.py
mock/fakemock_resolver.py
mock/mock.py
parser/__init__.py
parser/collection.py
parser/folder.py
parser/request.py
parser/requestitem.py
parser/response.py
spec/__init__.py
spec/operation.py
spec/plugins.py
spec/spec.py
swagmanmock/__init__.py
swagmanmock/cli.py
swagmanmock/errors.py
swagmanmock/schema_converter.py
swagmanmock/utils.py
swagmanmock/mock/__init__.py
swagmanmock/mock/fakemock_resolver.py
swagmanmock/mock/mock.py
swagmanmock/parser/__init__.py
swagmanmock/parser/collection.py
swagmanmock/parser/folder.py
swagmanmock/parser/request.py
swagmanmock/parser/requestitem.py
swagmanmock/parser/response.py
swagmanmock/spec/__init__.py
swagmanmock/spec/operation.py
swagmanmock/spec/plugins.py
swagmanmock/spec/spec.py
SwagmanMock-0.1.0.dist-info/METADATA
SwagmanMock-0.1.0.dist-info/WHEEL
SwagmanMock-0.1.0.dist-info/entry_points.txt
SwagmanMock-0.1.0.dist-info/top_level.txt
SwagmanMock-0.1.0.dist-info/RECORD
