Metadata-Version: 2.1
Name: SwagmanMock
Version: 0.1.0
Summary: A Postman to Swagger converter with mocking facilities
Home-page: https://github.com/codeasashu/swagmanmock
License: MIT
Keywords: api,openapi,swagger,rest,specification,oas,documentation
Platform: UNKNOWN
Classifier: Development Status :: 3 - Alpha
Classifier: Intended Audience :: Developers
Classifier: Topic :: Software Development :: Build Tools
Classifier: License :: OSI Approved :: MIT License
Classifier: Programming Language :: Python :: 3
Classifier: Programming Language :: Python :: 3.5
Classifier: Programming Language :: Python :: 3.6
Requires-Python: >=3.5
